mlotsawa/__init__.py
mlotsawa/translator.py
mlotsawa/transliterator.py
mlotsawa/webui.py
mlotsawa/static/favicon.ico
mlotsawa/static/styles/main.css
mlotsawa/templates/index.html
mlotsawa-0.4.3.dist-info/METADATA
mlotsawa-0.4.3.dist-info/WHEEL
mlotsawa-0.4.3.dist-info/licenses/LICENSE
mlotsawa-0.4.3.dist-info/RECORD
