Metadata-Version: 2.3
Name: mlotsawa
Version: 0.4.3
Summary: The purpose of this module is user-friendly translation and transliteration of Classical Tibetan.
Project-URL: Homepage, https://github.com/billingsmoore/MLotsawa
Project-URL: Issues, https://github.com/billingsmoore/MLotsawa/issues
Author-email: Jacob Moore <billingsmoore@gmail.com>
License-File: LICENSE
Classifier: License :: OSI Approved :: MIT License
Classifier: Operating System :: OS Independent
Classifier: Programming Language :: Python :: 3
Requires-Python: >=3.8
Requires-Dist: flask
Requires-Dist: threading
Requires-Dist: torch
Requires-Dist: transformers
Requires-Dist: waitress
Requires-Dist: webbrowser
